20191_ELEC247/Assignment3/sync_bcd_counter.v
// BCD counter module
// 2018112749 전현승
module sync_bcd_counter(Q8, Q4, Q2, Q1, TQ1, Clk, Rst_b);
  output Q8, Q4, Q2, Q1;  // 카운터 모듈의 output (각 flip flop의 output)
  input TQ1, Clk, Rst_b;  // 카운터 모듈의 input (Clk : Clock, Rst_b : Reset)
  wire TQ2, TQ4, TQ8;  // 각 flip flop의 input (TQ1 : test bench에서 초기값 지정. TQ2, TQ4, TQ8 : 변수)
  wire Q8Q1, Q4Q2Q1;  // 게이트 정의에서 임시로 쓰일 변수

  // 임시변수 정의
  and
    G1(Q8Q1, Q8, Q1),
    G2(Q4Q2Q1, Q4, Q2, Q1);

  // 각 flip flop의 input 정의
  and
    G3(TQ2, ~Q8, Q1),  // TQ2 = Q8'Q1
    G4(TQ4, Q2, Q1);  // TQ4 = Q2Q1
  or G5(TQ8, Q8Q1, Q4Q2Q1);  // TQ8 = Q8Q1 + Q4Q2Q1

  // 회로에 사용되는 T flip flop 4개 (동기식 : 같은 Clk 공유)
  Toggle_flip_flop F1 (Q1, TQ1, Clk, Rst_b);
  Toggle_flip_flop F2 (Q2, TQ2, Clk, Rst_b);
  Toggle_flip_flop F3 (Q4, TQ4, Clk, Rst_b);
  Toggle_flip_flop F4 (Q8, TQ8, Clk, Rst_b);
endmodule


// flip flop module
module Toggle_flip_flop (Q, T, Clk, Rst_b);
	output Q;  // flip flop의 output
	input T, Clk, Rst_b;  // flip flop의 input
	reg Q;
	always @ (posedge Clk, negedge Rst_b)  // Clk이 0->1이거나 Rst_b가 1->0인 경우
	  if (Rst_b == 0) Q <= 1'b0;  // Rst_b가 0이 된 경우라면 flip flop의 output = 0
	  else if (T) Q <= ~Q;  // Clk이 0->1이면서 flip flop의 입력이 1이라면 output을 toggle
endmodule

20191_ELEC247/Assignment3/t_sync_bcd_counter.v
// test bench
// 2018112749 전현승
module t_sync_bcd_counter;
  reg t_TQ1, t_Clk, t_Rst_b;  // 카운터 모듈에 들어갈 input
  wire t_Q8, t_Q4, t_Q2, t_Q1;  // 카운터 모듈에서 나올 output

  // 카운터 모듈 instantiate
  sync_bcd_counter M (t_Q8, t_Q4, t_Q2, t_Q1, t_TQ1, t_Clk, t_Rst_b);

  always #10 t_Clk = ~t_Clk;  // 모듈에 들어가는 Clk을 10ns 단위로 toggle

  initial begin
    // 모든 변수 변경 내역을 dump.vcd에 저장
    $dumpfile("dump.vcd");
    $dumpvars(0, t_sync_bcd_counter);

    t_TQ1 = 1'b1;  // 모듈의 1번 flip flop (F1)의 input : 항상 1
    t_Clk = 1'b0;  // Clk 초기값 설정
    t_Rst_b = 1'b0;  
    #5 t_Rst_b = 1'b1;  // Rst 초기값 0 설정 후, Clk 사이클 시작 전에 1로 변경
  end

  initial #400 $finish;  // 실행 400ns 경과 후 종료

  initial begin
    // 모듈 output 바뀔 때마다 output 비트 4개 출력 (Q8, Q4, Q2, Q1 순서)
    $monitor ("%b %b %b %b", t_Q8, t_Q4, t_Q2, t_Q1);
  end
endmodule

20191_ELEC247/Assignment3/dump.vcd
$date
	Thu May 30 23:20:38 2019
$end
$version
	Icarus Verilog
$end
$timescale
	1s
$end
$scope module t_sync_bcd_counter $end
$var wire 1 ! t_Q8 $end
$var wire 1 " t_Q4 $end
$var wire 1 # t_Q2 $end
$var wire 1 $ t_Q1 $end
$var reg 1 % t_Clk $end
$var reg 1 & t_Rst_b $end
$var reg 1 ' t_TQ1 $end
$scope module M $end
$var wire 1 % Clk $end
$var wire 1 ( Q4Q2Q1 $end
$var wire 1 ) Q8Q1 $end
$var wire 1 & Rst_b $end
$var wire 1 ' TQ1 $end
$var wire 1 * TQ2 $end
$var wire 1 + TQ4 $end
$var wire 1 , TQ8 $end
$var wire 1 ! Q8 $end
$var wire 1 " Q4 $end
$var wire 1 # Q2 $end
$var wire 1 $ Q1 $end
$scope module F1 $end
$var wire 1 % Clk $end
$var wire 1 & Rst_b $end
$var wire 1 ' T $end
$var reg 1 $ Q $end
$upscope $end
$scope module F2 $end
$var wire 1 % Clk $end
$var wire 1 & Rst_b $end
$var wire 1 * T $end
$var reg 1 # Q $end
$upscope $end
$scope module F3 $end
$var wire 1 % Clk $end
$var wire 1 & Rst_b $end
$var wire 1 + T $end
$var reg 1 " Q $end
$upscope $end
$scope module F4 $end
$var wire 1 % Clk $end
$var wire 1 & Rst_b $end
$var wire 1 , T $end
$var reg 1 ! Q $end
$upscope $end
$upscope $end
$upscope $end
$enddefinitions $end
#0
$dumpvars
0,
0+
0*
0)
0(
1'
0&
0%
0$
0#
0"
0!
$end
#5
1&
#10
1*
1$
1%
#20
0%
#30
0*
0$
1#
1%
#40
0%
#50
1+
1*
1$
1%
#60
0%
#70
0*
0+
0$
0#
1"
1%
#80
0%
#90
1*
1$
1%
#100
0%
#110
0*
0$
1#
1%
#120
0%
#130
1,
1+
1*
1(
1$
1%
#140
0%
#150
0,
0*
0+
0(
0$
0#
0"
1!
1%
#160
0%
#170
1,
1)
1$
1%
#180
0%
#190
0,
0)
0$
0!
1%
#200
0%
#210
1*
1$
1%
#220
0%
#230
0*
0$
1#
1%
#240
0%
#250
1+
1*
1$
1%
#260
0%
#270
0*
0+
0$
0#
1"
1%
#280
0%
#290
1*
1$
1%
#300
0%
#310
0*
0$
1#
1%
#320
0%
#330
1,
1+
1*
1(
1$
1%
#340
0%
#350
0,
0*
0+
0(
0$
0#
0"
1!
1%
#360
0%
#370
1,
1)
1$
1%
#380
0%
#390
0,
0)
0$
0!
1%
